VERSION.py
main_funcs.py
markify.py
util_funcs.py
markify-1.0.4.dist-info/LICENSE.txt
markify-1.0.4.dist-info/METADATA
markify-1.0.4.dist-info/WHEEL
markify-1.0.4.dist-info/entry_points.txt
markify-1.0.4.dist-info/top_level.txt
markify-1.0.4.dist-info/RECORD
