Metadata-Version: 2.1
Name: markify
Version: 1.0.4
Summary: Markify is an open source command line application written in python which scrapes data from your social media(s) (ie reddit, discord, and twitter for now) and generates new setences based on them using markov chains. For more information, please visit https://github.com/msr8/markify
Project-URL: Bug Tracker, https://github.com/msr8/markify/issues
Project-URL: Source Code, https://github.com/msr8/markify
Platform: Windows
Platform: Linux
Platform: Solaris
Platform: Mac OS-X
Platform: Unix
Classifier: Programming Language :: Python :: 3
Classifier: Programming Language :: Python :: 3.6
Classifier: Programming Language :: Python :: 3.7
Classifier: Programming Language :: Python :: 3.8
Classifier: Programming Language :: Python :: 3.9
Classifier: Programming Language :: Python :: 3.10
Classifier: License :: OSI Approved :: GNU General Public License v3 (GPLv3)
Classifier: Operating System :: OS Independent
Classifier: Operating System :: Microsoft :: Windows
Classifier: Operating System :: POSIX
Classifier: Operating System :: Unix
Classifier: Operating System :: MacOS
License-File: LICENSE.txt
Requires-Dist: colorama
Requires-Dist: rich
Requires-Dist: snscrape
Requires-Dist: tqdm
Requires-Dist: markovify
Requires-Dist: nltk
